[
    {
        "nama": "SLB ABDUL MUCHYI",
        "sekolah_id": "E110719F-1217-4814-879B-884EA2B731E2",
        "npsn": 69894293,
        "jumlah_kirim": 10,
        "ptk": 5,
        "pegawai": 3,
        "pd": 41,
        "rombel": 10,
        "jml_rk": 4,
        "jml_lab": 0,
        "jml_perpus": 1,
        "induk_kecamatan": "Kec. Kadipaten",
        "kode_wilayah_induk_kecamatan": "021617  ",
        "induk_kabupaten": "Kab. Majalengka",
        "kode_wilayah_induk_kabupaten": "021600  ",
        "induk_provinsi": "Prov. Jawa Barat",
        "kode_wilayah_induk_provinsi": "020000  ",
        "bentuk_pendidikan": "SLB",
        "status_sekolah": "Swasta",
        "sinkron_terakhir": "29 Aug 2025 01:11:34",
        "sekolah_id_enkrip": "9ACBC85011AD0F698E53                                                                                "
    }
]