[
    {
        "nama": "SLB BAKTI PERTIWI",
        "sekolah_id": "202ADA15-2CF5-E011-9AD5-AD3FAD197C13",
        "npsn": 20258142,
        "jumlah_kirim": 7,
        "ptk": 9,
        "pegawai": 1,
        "pd": 89,
        "rombel": 12,
        "jml_rk": 6,
        "jml_lab": 0,
        "jml_perpus": 1,
        "induk_kecamatan": "Kec. Kadudampit",
        "kode_wilayah_induk_kecamatan": "020619  ",
        "induk_kabupaten": "Kab. Sukabumi",
        "kode_wilayah_induk_kabupaten": "020600  ",
        "induk_provinsi": "Prov. Jawa Barat",
        "kode_wilayah_induk_provinsi": "020000  ",
        "bentuk_pendidikan": "SLB",
        "status_sekolah": "Swasta",
        "sinkron_terakhir": "08 Aug 2025 19:54:11",
        "sekolah_id_enkrip": "2824B754CB8C8A77A3A1                                                                                "
    }
]