[
    {
        "nama": "SLB AL FITHRI",
        "sekolah_id": "E0D7DC15-2CF5-E011-80F6-9BB5F1DAF632",
        "npsn": 20258470,
        "jumlah_kirim": 9,
        "ptk": 7,
        "pegawai": 2,
        "pd": 56,
        "rombel": 14,
        "jml_rk": 4,
        "jml_lab": 1,
        "jml_perpus": 0,
        "induk_kecamatan": "Kec. Cimaung",
        "kode_wilayah_induk_kecamatan": "020803  ",
        "induk_kabupaten": "Kab. Bandung",
        "kode_wilayah_induk_kabupaten": "020800  ",
        "induk_provinsi": "Prov. Jawa Barat",
        "kode_wilayah_induk_provinsi": "020000  ",
        "bentuk_pendidikan": "SLB",
        "status_sekolah": "Swasta",
        "sinkron_terakhir": "26 Aug 2025 19:26:57",
        "sekolah_id_enkrip": "C7F6104262BD37649C0C                                                                                "
    },
    {
        "nama": "SLB MIFTAHUL FALAH",
        "sekolah_id": "2001E435-4303-E211-ACDD-316CC6E6772B",
        "npsn": 20259611,
        "jumlah_kirim": 14,
        "ptk": 4,
        "pegawai": 2,
        "pd": 39,
        "rombel": 11,
        "jml_rk": 6,
        "jml_lab": 0,
        "jml_perpus": 1,
        "induk_kecamatan": "Kec. Cimaung",
        "kode_wilayah_induk_kecamatan": "020803  ",
        "induk_kabupaten": "Kab. Bandung",
        "kode_wilayah_induk_kabupaten": "020800  ",
        "induk_provinsi": "Prov. Jawa Barat",
        "kode_wilayah_induk_provinsi": "020000  ",
        "bentuk_pendidikan": "SLB",
        "status_sekolah": "Swasta",
        "sinkron_terakhir": "19 Aug 2025 17:58:57",
        "sekolah_id_enkrip": "214511E6897A0FDA614E                                                                                "
    }
]