[
    {
        "nama": "SKH NEGERI 1 SANAMAN MANTIKEI",
        "sekolah_id": "AFB48E1D-3CFA-4278-9941-6931B9667C01",
        "npsn": 70056430,
        "jumlah_kirim": 0,
        "ptk": 7,
        "pegawai": 2,
        "pd": 0,
        "rombel": 0,
        "jml_rk": 0,
        "jml_lab": 0,
        "jml_perpus": 0,
        "induk_kecamatan": "Kec. Sanaman Mantikei",
        "kode_wilayah_induk_kecamatan": "140611  ",
        "induk_kabupaten": "Kab. Katingan",
        "kode_wilayah_induk_kabupaten": "140600  ",
        "induk_provinsi": "Prov. Kalimantan Tengah",
        "kode_wilayah_induk_provinsi": "140000  ",
        "bentuk_pendidikan": "SLB",
        "status_sekolah": "Negeri",
        "sinkron_terakhir": null,
        "sekolah_id_enkrip": "533BA1FCB643FEBD33E6                                                                                "
    }
]