[
    {
        "nama": "SLB SINAR HARAPAN 2",
        "sekolah_id": "60AD4C7E-8D18-E111-A67E-659A94A93E6D",
        "npsn": 20536264,
        "jumlah_kirim": 5,
        "ptk": 9,
        "pegawai": 3,
        "pd": 40,
        "rombel": 10,
        "jml_rk": 7,
        "jml_lab": 1,
        "jml_perpus": 1,
        "induk_kecamatan": "Kec. Kademangan",
        "kode_wilayah_induk_kecamatan": "056701  ",
        "induk_kabupaten": "Kota Probolinggo",
        "kode_wilayah_induk_kabupaten": "056700  ",
        "induk_provinsi": "Prov. Jawa Timur",
        "kode_wilayah_induk_provinsi": "050000  ",
        "bentuk_pendidikan": "SLB",
        "status_sekolah": "Swasta",
        "sinkron_terakhir": "14 Aug 2025 12:21:10",
        "sekolah_id_enkrip": "4ED7A306EFF4878247FA                                                                                "
    }
]