[
    {
        "nama": "SLB - B NGUDI HAYU",
        "sekolah_id": "E0F6B215-54BF-E111-96C4-EF3EBE0F0B71",
        "npsn": 20549314,
        "jumlah_kirim": 22,
        "ptk": 3,
        "pegawai": 1,
        "pd": 29,
        "rombel": 13,
        "jml_rk": 4,
        "jml_lab": 0,
        "jml_perpus": 1,
        "induk_kecamatan": "Kec. Srengat",
        "kode_wilayah_induk_kecamatan": "051520  ",
        "induk_kabupaten": "Kab. Blitar",
        "kode_wilayah_induk_kabupaten": "051500  ",
        "induk_provinsi": "Prov. Jawa Timur",
        "kode_wilayah_induk_provinsi": "050000  ",
        "bentuk_pendidikan": "SLB",
        "status_sekolah": "Swasta",
        "sinkron_terakhir": "28 Aug 2025 16:23:31",
        "sekolah_id_enkrip": "B53CD46DA3104FDA6725                                                                                "
    },
    {
        "nama": "SLB-C.D NGUDI HAYU",
        "sekolah_id": "E0BA6FBB-8C18-E111-B3DD-D155381BD573",
        "npsn": 20549289,
        "jumlah_kirim": 13,
        "ptk": 8,
        "pegawai": 1,
        "pd": 80,
        "rombel": 16,
        "jml_rk": 6,
        "jml_lab": 0,
        "jml_perpus": 1,
        "induk_kecamatan": "Kec. Srengat",
        "kode_wilayah_induk_kecamatan": "051520  ",
        "induk_kabupaten": "Kab. Blitar",
        "kode_wilayah_induk_kabupaten": "051500  ",
        "induk_provinsi": "Prov. Jawa Timur",
        "kode_wilayah_induk_provinsi": "050000  ",
        "bentuk_pendidikan": "SLB",
        "status_sekolah": "Swasta",
        "sinkron_terakhir": "27 Aug 2025 20:54:28",
        "sekolah_id_enkrip": "4721C78ECD4D269A6EB6                                                                                "
    }
]