[
    {
        "nama": "SLBN 1 RANAH PESISIR",
        "sekolah_id": "C0B3EF79-2FF5-E011-B963-27D7BCD5316F",
        "npsn": 10308223,
        "jumlah_kirim": 28,
        "ptk": 13,
        "pegawai": 2,
        "pd": 61,
        "rombel": 13,
        "jml_rk": 5,
        "jml_lab": 0,
        "jml_perpus": 1,
        "induk_kecamatan": "Kec. Ranah Pesisir",
        "kode_wilayah_induk_kecamatan": "080605  ",
        "induk_kabupaten": "Kab. Pesisir Selatan",
        "kode_wilayah_induk_kabupaten": "080600  ",
        "induk_provinsi": "Prov. Sumatera Barat",
        "kode_wilayah_induk_provinsi": "080000  ",
        "bentuk_pendidikan": "SLB",
        "status_sekolah": "Negeri",
        "sinkron_terakhir": "20 Aug 2025 22:27:47",
        "sekolah_id_enkrip": "6BE521C288EF22D215E2                                                                                "
    },
    {
        "nama": "SLB Hazirah Ranah Pesisir",
        "sekolah_id": "92D746DE-E023-4902-9F01-4D1383021B54",
        "npsn": 70014420,
        "jumlah_kirim": 30,
        "ptk": 5,
        "pegawai": 2,
        "pd": 34,
        "rombel": 5,
        "jml_rk": 5,
        "jml_lab": 0,
        "jml_perpus": 1,
        "induk_kecamatan": "Kec. Ranah Pesisir",
        "kode_wilayah_induk_kecamatan": "080605  ",
        "induk_kabupaten": "Kab. Pesisir Selatan",
        "kode_wilayah_induk_kabupaten": "080600  ",
        "induk_provinsi": "Prov. Sumatera Barat",
        "kode_wilayah_induk_provinsi": "080000  ",
        "bentuk_pendidikan": "SLB",
        "status_sekolah": "Swasta",
        "sinkron_terakhir": "27 Aug 2025 20:24:56",
        "sekolah_id_enkrip": "8896FF61D523B2D0F7F7                                                                                "
    }
]