[
    {
        "nama": "SLB A BARTEMEUS",
        "sekolah_id": "F0BDE1AC-30F5-E011-82A3-FD35C9FF9801",
        "npsn": 40103411,
        "jumlah_kirim": 9,
        "ptk": 8,
        "pegawai": 1,
        "pd": 33,
        "rombel": 11,
        "jml_rk": 22,
        "jml_lab": 1,
        "jml_perpus": 1,
        "induk_kecamatan": "Kec. Malalayang",
        "kode_wilayah_induk_kecamatan": "176001  ",
        "induk_kabupaten": "Kota Manado",
        "kode_wilayah_induk_kabupaten": "176000  ",
        "induk_provinsi": "Prov. Sulawesi Utara",
        "kode_wilayah_induk_provinsi": "170000  ",
        "bentuk_pendidikan": "SLB",
        "status_sekolah": "Swasta",
        "sinkron_terakhir": "22 Aug 2025 06:37:21",
        "sekolah_id_enkrip": "B39BAB453A2A1F7506D7                                                                                "
    },
    {
        "nama": "SLB YPAC MANADO",
        "sekolah_id": "A0D7E1AC-30F5-E011-9887-635ED1C5BAC3",
        "npsn": 40104552,
        "jumlah_kirim": 43,
        "ptk": 13,
        "pegawai": 2,
        "pd": 52,
        "rombel": 19,
        "jml_rk": 15,
        "jml_lab": 0,
        "jml_perpus": 1,
        "induk_kecamatan": "Kec. Malalayang",
        "kode_wilayah_induk_kecamatan": "176001  ",
        "induk_kabupaten": "Kota Manado",
        "kode_wilayah_induk_kabupaten": "176000  ",
        "induk_provinsi": "Prov. Sulawesi Utara",
        "kode_wilayah_induk_provinsi": "170000  ",
        "bentuk_pendidikan": "SLB",
        "status_sekolah": "Swasta",
        "sinkron_terakhir": "01 Aug 2025 20:47:52",
        "sekolah_id_enkrip": "2EAC7D4D8650C9B482D5                                                                                "
    }
]